pyfmma.pypy310-pp73-x86-linux-gnu.so
pyfmma-0.1.2.dist-info/RECORD
pyfmma-0.1.2.dist-info/top_level.txt
pyfmma-0.1.2.dist-info/METADATA
pyfmma-0.1.2.dist-info/LICENSE
pyfmma-0.1.2.dist-info/WHEEL
