Metadata-Version: 2.1
Name: pyfmma
Version: 0.1.2
Summary: pyfmma: Fast Multipole Method for arbitrary functions
Home-page: https://github.com/fockl/FMMA
Download-URL: https://github.com/fockl/FMMA
Author: fockl
Author-email: j4xn3gvbxqtfdnxg@gmail.com
License: MIT
Classifier: License :: OSI Approved :: MIT License
Classifier: Programming Language :: C++
Classifier: Programming Language :: Python
License-File: LICENSE
Requires-Dist: setuptools <72.2.0
Requires-Dist: pybind11
